events_manager/__init__.py
events_manager/event.py
events_manager-0.2.2.dist-info/LICENSE
events_manager-0.2.2.dist-info/METADATA
events_manager-0.2.2.dist-info/WHEEL
events_manager-0.2.2.dist-info/top_level.txt
events_manager-0.2.2.dist-info/RECORD
