Metadata-Version: 2.1
Name: events-manager
Version: 0.2.2
Summary: Python implementation for the Events Management system (aka Observer pattern)
Home-page: https://github.com/webfucktory/python-events-manager
Author: webfucktory
Author-email: root@webfucktory.com
Classifier: Development Status :: 5 - Production/Stable
Classifier: Intended Audience :: Developers
Classifier: Natural Language :: English
Classifier: Operating System :: OS Independent
Classifier: Programming Language :: Python :: 3
Classifier: Programming Language :: Python :: 3.8
Classifier: Programming Language :: Python :: 3.9
Classifier: Programming Language :: Python :: 3 :: Only
Requires-Python: >=3.8
License-File: LICENSE
